starlight/__init__.py
starlight/cli/__init__.py
starlight/cli/cache.py
starlight/cli/chart.py
starlight/cli/ephemeris.py
starlight/cli/ephemeris_download.py
starlight/components/__init__.py
starlight/components/arabic_parts.py
starlight/components/dignity.py
starlight/components/midpoints.py
starlight/core/__init__.py
starlight/core/builder.py
starlight/core/comparison.py
starlight/core/config.py
starlight/core/models.py
starlight/core/native.py
starlight/core/protocols.py
starlight/core/registry.py
starlight/data/__init__.py
starlight/data/registry.py
starlight/engines/__init__.py
starlight/engines/aspects.py
starlight/engines/dignities.py
starlight/engines/ephemeris.py
starlight/engines/houses.py
starlight/engines/orbs.py
starlight/engines/patterns.py
starlight/presentation/__init__.py
starlight/presentation/builder.py
starlight/presentation/renderers.py
starlight/presentation/sections.py
starlight/utils/__init__.py
starlight/utils/cache.py
starlight/utils/cache_utils.py
starlight/utils/houses.py
starlight/visualization/__init__.py
starlight/visualization/core.py
starlight/visualization/drawing.py
starlight/visualization/layers.py
starlight/visualization/moon_phase.py
starlight_astro-0.2.0.dist-info/licenses/LICENSE
starlight_astro-0.2.0.dist-info/METADATA
starlight_astro-0.2.0.dist-info/WHEEL
starlight_astro-0.2.0.dist-info/entry_points.txt
starlight_astro-0.2.0.dist-info/top_level.txt
starlight_astro-0.2.0.dist-info/RECORD
