Metadata-Version: 2.4
Name: starlight-astro
Version: 0.2.0
Summary: A modern Python library for astrological chart calculation and visualization, built on the Swiss Ephemeris for astronomical accuracy.
Author-email: Kate Louie <katehlouie@gmail.com>
License-Expression: MIT
Project-URL: Homepage, https://github.com/katelouie/starlight
Project-URL: Repository, https://github.com/katelouie/starlight
Project-URL: Documentation, https://github.com/katelouie/starlight
Project-URL: Bug Tracker, https://github.com/katelouie/starlight/issues
Keywords: astrology,horoscope,chart,swiss-ephemeris,astronomy,natal-chart,arabic-parts
Classifier: Development Status :: 4 - Beta
Classifier: Intended Audience :: Developers
Classifier: Intended Audience :: Science/Research
Classifier: Programming Language :: Python :: 3
Classifier: Programming Language :: Python :: 3.11
Classifier: Programming Language :: Python :: 3.12
Classifier: Topic :: Scientific/Engineering :: Astronomy
Classifier: Topic :: Software Development :: Libraries :: Python Modules
Requires-Python: >=3.11
License-File: LICENSE
Requires-Dist: pyswisseph>=2.10.3
Requires-Dist: pytz>=2024.1
Requires-Dist: timezonefinder>=6.5.0
Requires-Dist: geopy>=2.4.0
Requires-Dist: rich>=13.9.0
Requires-Dist: svgwrite>=1.4.3
Requires-Dist: pyyaml
Provides-Extra: dev
Requires-Dist: pytest>=8.0.0; extra == "dev"
Requires-Dist: pytest-cov>=4.0.0; extra == "dev"
Requires-Dist: black>=24.0.0; extra == "dev"
Requires-Dist: ruff>=0.1.0; extra == "dev"
Requires-Dist: isort>=5.13.0; extra == "dev"
Requires-Dist: mypy>=1.8.0; extra == "dev"
Requires-Dist: pre-commit>=3.6.0; extra == "dev"
Provides-Extra: docs
Requires-Dist: mkdocs>=1.5.0; extra == "docs"
Requires-Dist: mkdocs-material>=9.5.0; extra == "docs"
Dynamic: license-file
